README.md
setup.cfg
setup.py
ordrbook/__init__.py
ordrbook/book.py
ordrbook/order.py
ordrbook/orderbook.py
ordrbook/queue.py
ordrbook.egg-info/PKG-INFO
ordrbook.egg-info/SOURCES.txt
ordrbook.egg-info/dependency_links.txt
ordrbook.egg-info/requires.txt
ordrbook.egg-info/top_level.txt