Metadata-Version: 1.1
Name: ordrbook
Version: 0.0.1
Summary: Limit Order Book
Home-page: https://github.com/tomcusack1/ordrbook
Author: Tom Cusack-Huang
Author-email: tom@cusack-huang.com
License: UNKNOWN
Download-URL: https://github.com/tomcusack1/ordrbook/archive/v_001.tar.gz
Platform: UNKNOWN
